refile testing/define.v
// Global macros
`define RST_EN      1'B1
`define TRUE        1'B1
`define FALSE       1'B0
`define SAOK        3'B000
`define SINS        3'B001
`define SADR        3'B010
`define SHLT        3'B100

// Instruction codes
`define HALT    4'H0
`define NOP     4'H1
`define CXX     4'H2
`define IXX     4'H3  //name to be changed
`define RMMOVQ  4'H4
`define MRMOVQ  4'H5
`define OPQ     4'H6
`define JXX     4'H7
`define CALL    4'H8
`define RET     4'H9
`define PUSHQ   4'HA
`define POPQ    4'HB

// Instruction functions
`define RRMOVQ  4'H0
`define CMOVLE  4'H1
`define CMOVL   4'H2
`define CMOVE   4'H3
`define CMOVNE  4'H4
`define CMOVGE  4'H5
`define CMOVG   4'H6

`define IRMOVQ  4'H0
`define IADDQ   4'H1
`define ISUBQ   4'H2
`define IANDQ   4'H3
`define IXORQ   4'H4

`define ADDQ    4'H0
`define SUBQ    4'H1
`define ANDQ    4'H2
`define XORQ    4'H3
`define NOPQ    4'H4

`define JMP     4'H0
`define JLE     4'H1
`define JL      4'H2
`define JE      4'H3
`define JNE     4'H4
`define JGE     4'H5
`define JG      4'H6

// Registers
`define RAX     4'H0
`define RBX     4'H3
`define RCX     4'H1
`define RDX     4'H2
`define RSP     4'H4
`define RBP     4'H5
`define RSI     4'H6
`define RDI     4'H7
`define R8      4'H8
`define R9      4'H9
`define R10     4'HA
`define R11     4'HB
`define R12     4'HC
`define R13     4'HD
`define R14     4'HE
`define NREG    4'HF

// Data width
`define ICODE_WIDTH     4
`define IFUN_WIDTH      4
`define BYTE_WIDTH      8
`define ADDR_WIDTH      64
`define DATA_WIDTH      64
`define INST_WIDTH      80

// Buses
`define IFUN_BUS        3:0
`define ICODE_BUS       3:0
`define REG_ADDR_BUS    3:0
`define ADDR_BUS        63:0
`define INST_BUS        79:0
`define DATA_BUS        63:0
`define STAT_BUS        2:0

// Instruction parts
`define ICODE           79:76
`define IFUN            75:72
`define SRCA            71:68
`define SRCB            67:64
`define BYTE8           71:64
`define BYTE7           63:56
`define BYTE6           55:48
`define BYTE5           47:40
`define BYTE4           39:32
`define BYTE3           31:24
`define BYTE2           23:16
`define BYTE1           15:8
`define BYTE0           7:0

// Memory size
`define MEM_SIZE        131071

// Default values
`define ICODE_ZERO      `ICODE_WIDTH'H0
`define IFUN_ZERO       `IFUN_WIDTH'H0
`define DATA_ZERO       `DATA_WIDTH'H0
`define ADDR_ZERO       `ADDR_WIDTH'H0
`define NONE_INST       `INST_WIDTH'H0
`define BYTE_ZERO       `BYTE_WIDTH'H0

fetch.v
`include "define.v"

module fetch(
    input wire [`ADDR_BUS] f_pc_i,
    input wire [`INST_BUS] inst_i,
    input wire mem_error_i,
    
    output reg [`ICODE_BUS] f_icode_o,
    output reg [`IFUN_BUS] f_ifun_o,
    output reg [`REG_ADDR_BUS] f_rA_o,
    output reg [`REG_ADDR_BUS] f_rB_o,
    output reg [`DATA_BUS] f_valC_o,
    output reg [`ADDR_BUS] f_valP_o,
    //output reg [`REG_ADDR_BUS] f_dstE_o,
    //output reg [`REG_ADDR_BUS] f_dstM_o,
    output reg [`ADDR_BUS] f_predPC_o,
    output reg [`STAT_BUS] f_stat_o
    );
    
    always @(f_pc_i, inst_i, mem_error_i)
    begin
        f_icode_o = inst_i[`ICODE];
        f_ifun_o = inst_i[`IFUN];
        f_rA_o = `NREG;
        f_rB_o = `NREG;
        f_valC_o = `DATA_ZERO;
        f_valP_o = `DATA_ZERO;
        //f_dstE_o = `NREG;
        //f_dstM_o = `NREG;
        f_stat_o = `SAOK;
        f_predPC_o = `ADDR_ZERO;
        if(mem_error_i == `FALSE)
        begin
            case(f_icode_o)
                `HALT:
                    begin
                        f_valP_o = f_pc_i + `ADDR_WIDTH'H1;
                        f_predPC_o = f_valP_o;
                        f_stat_o = `SHLT;   //Status code for halt
                    end
                `NOP:
                    begin
                        f_valP_o = f_pc_i + `ADDR_WIDTH'H1;
                        f_predPC_o = f_valP_o;
                        f_stat_o = `SAOK;   //Status code for normal operation
                    end
                `CXX:
                    begin
                        f_rA_o = inst_i[`SRCA];
                        f_rB_o = inst_i[`SRCB];
                        f_valP_o = f_pc_i + `ADDR_WIDTH'H2;
                        f_predPC_o = f_valP_o;
                        //f_dstE_o = f_rB_o; //coz we are using blocking assignment, f_rB_o we be evaluated first
                        f_stat_o = `SAOK;
                    end
                `OPQ:
                    begin
                        f_rA_o = inst_i[`SRCA];
                        f_rB_o = inst_i[`SRCB];
                        f_valP_o = f_pc_i + `ADDR_WIDTH'H2;
                        f_predPC_o = f_valP_o;
                        //f_dstE_o = f_rB_o;
                        f_stat_o = `SAOK;
                    end
                `IXX:
                    begin
                        f_rA_o = inst_i[`SRCA];//rA not needed here
                        f_rB_o = inst_i[`SRCB];
                        f_valC_o = {inst_i[`BYTE0], inst_i[`BYTE1], inst_i[`BYTE2], inst_i[`BYTE3],
                                    inst_i[`BYTE4], inst_i[`BYTE5], inst_i[`BYTE6], inst_i[`BYTE7]};
                        f_valP_o = f_pc_i + `ADDR_WIDTH'HA;
                        f_predPC_o = f_valP_o;
                        //f_dstE_o = f_rB_o;
                        f_stat_o = `SAOK;
                    end
                `RMMOVQ:
                    begin
                        f_rA_o = inst_i[`SRCA];
                        f_rB_o = inst_i[`SRCB];
                        f_valC_o = {inst_i[`BYTE0], inst_i[`BYTE1], inst_i[`BYTE2], inst_i[`BYTE3],
                                    inst_i[`BYTE4], inst_i[`BYTE5], inst_i[`BYTE6], inst_i[`BYTE7]};
                        f_valP_o = f_pc_i + `ADDR_WIDTH'HA;
                        f_predPC_o = f_valP_o;
                        f_stat_o = `SAOK;
                    end
                `MRMOVQ:
                    begin
                        f_rA_o = inst_i[`SRCA];
                        f_rB_o = inst_i[`SRCB];
                        f_valC_o = {inst_i[`BYTE0], inst_i[`BYTE1], inst_i[`BYTE2], inst_i[`BYTE3],
                                    inst_i[`BYTE4], inst_i[`BYTE5], inst_i[`BYTE6], inst_i[`BYTE7]};
                        f_valP_o = f_pc_i + `ADDR_WIDTH'HA;
                        f_predPC_o = f_valP_o;
                        //f_dstM_o = f_rB_o;
                        f_stat_o = `SAOK;
                    end
                `JXX:
                    begin
                        f_valC_o = {inst_i[`BYTE1], inst_i[`BYTE2], inst_i[`BYTE3], inst_i[`BYTE4],
                                    inst_i[`BYTE5], inst_i[`BYTE6], inst_i[`BYTE7], inst_i[`BYTE8]};
                        f_valP_o = f_pc_i + `ADDR_WIDTH'H9;
                        f_predPC_o = f_valC_o;
                        f_stat_o = `SAOK;
                    end
                 `CALL:
                    begin
                        f_rA_o = `RSP;
                        f_rB_o = `RSP;
                        f_valC_o = {inst_i[`BYTE1], inst_i[`BYTE2], inst_i[`BYTE3], inst_i[`BYTE4],
                                    inst_i[`BYTE5], inst_i[`BYTE6], inst_i[`BYTE7], inst_i[`BYTE8]};
                        f_valP_o = f_pc_i + `ADDR_WIDTH'H9;
                        f_predPC_o = f_valC_o;
                        //f_dstE_o = `RSP;
                        f_stat_o = `SAOK;
                    end
                `RET:
                    begin
                        f_rA_o = `RSP;
                        f_rB_o = `RSP;
                        f_valP_o = f_pc_i + `ADDR_WIDTH'H1;
                        //f_dstE_o = `RSP;
                        f_stat_o = `SAOK;
                    end
                `PUSHQ:
                    begin
                        f_rA_o = inst_i[`SRCA];
                        f_rB_o = `RSP;
                        f_valP_o = f_pc_i + `ADDR_WIDTH'H2;
                        f_predPC_o = f_valP_o;
                        //f_dstE_o = `RSP;
                        f_stat_o = `SAOK;
                    end
                `POPQ:
                    begin
                        f_rA_o = inst_i[`SRCA];//f_rA_o = `RSP;
                        f_rB_o = `RSP;
                        f_valP_o = f_pc_i + `ADDR_WIDTH'H2;
                        f_predPC_o = f_valP_o;
                        //f_dstE_o = `RSP;
                        //f_dstM_o = inst_i[`SRCA];
                        f_stat_o = `SAOK;
                    end
                default:
                    begin   
                        f_valP_o = f_pc_i + `ADDR_WIDTH'H1;
                        f_predPC_o = f_valP_o;
                        f_stat_o = `SINS;   //Status code for illegal instruction exception
                    end
            endcase
        end
        else
        begin
            f_stat_o = `SADR;  //Status code for address exception
        end
    end

endmodule

testing/fetch_tb.v
`timescale 1ns / 1ps

module fetch_tb;
        // Inputs
        reg [79:0] inst;
	reg [63:0] f_pc;
        reg mem_error;
        // Outputs
        wire [3:0] f_icode,f_ifun,f_rA,f_rB;
        wire [63:0] f_valC,f_valP,f_predPC;
	wire [2:0] f_stat;

        fetch fetch0(
            .f_pc_i(f_pc),
            .inst_i(inst),
            .mem_error_i(mem_error),

            .f_icode_o(f_icode),
            .f_ifun_o(f_ifun),
            .f_rA_o(f_rA),
            .f_rB_o(f_rB),
            .f_valC_o(f_valC),
            .f_valP_o(f_valP),
            .f_predPC_o(f_predPC),
            .f_stat_o(f_stat)
      );
	
	initial begin
                // Initialize Inputs
                $dumpfile("fetch_tb.vcd");
                $dumpvars(0,fetch_tb);
		//clk <= 1'B0;
		mem_error <= 1'B0;
		f_pc <= 64'B001;
		inst <= 80'H00560000000000000000;
		#50;
		//clk <= 1'B1;
		mem_error <= 1'B0;
                f_pc <= 64'B001;
                inst <= 80'H10560000000000000000;
		#50
		mem_error <= 1'B0;
                f_pc <= 64'B001;
                inst <= 80'H20560000000000000000;
                #50;
		mem_error <= 1'B0;
                f_pc <= 64'B001;
                inst <= 80'H30560000000000000009;
                #50;
		mem_error <= 1'B0;
                f_pc <= 64'B001;
                inst <= 80'H40560000000000000107;
                #50;
		mem_error <= 1'B0;
                f_pc <= 64'B001;
                inst <= 80'H50560000000000000100;
                #50;
		mem_error <= 1'B0;
                f_pc <= 64'B001;
                inst <= 80'H60560000000000000000;
                #50;
		mem_error <= 1'B0;
                f_pc <= 64'B001;
                inst <= 80'H70560000000000000020;
                #50;
		mem_error <= 1'B0;
                f_pc <= 64'B001;
                inst <= 80'H80560000000000000031;
                #50;
		mem_error <= 1'B0;
                f_pc <= 64'B001;
                inst <= 80'H90560000000000000000;
                #50;
		mem_error <= 1'B0;
                f_pc <= 64'B001;
                inst <= 80'HA0560000000000000000;
                #50;
		mem_error <= 1'B0;
                f_pc <= 64'B001;
                inst <= 80'HB0560000000000000000;
                #50;
                // Wait 100 ns for global reset to finish
                #100;

                // Add stimulus here
                /*#20 b=1;
                #20 a=1;b=0;
                #20 b=1;
                #20 a=0;b=0;cin=1;
                #20 b=1;
                #20 a=1;b=0;
                #20 b=1;*/
        end
	initial begin
		$monitor("f_pc=%d inst=%h mem_error=%d f_icode=%d f_ifun=%d f_rA=%d f_rB=%d f_valC=%d f_valP=%d f_predPC=%d f_stat=%d\n",f_pc,inst,mem_error,f_icode,f_ifun,f_rA,f_rB,f_valC,f_valP,f_predPC,f_stat);
 
	end
 endmodule

testing/fetch_tb.vcd
$date
	Tue Mar  9 00:06:07 2021
$end
$version
	Icarus Verilog
$end
$timescale
	1ps
$end
$scope module fetch_tb $end
$var wire 64 ! f_valP [63:0] $end
$var wire 64 " f_valC [63:0] $end
$var wire 3 # f_stat [2:0] $end
$var wire 4 $ f_rB [3:0] $end
$var wire 4 % f_rA [3:0] $end
$var wire 64 & f_predPC [63:0] $end
$var wire 4 ' f_ifun [3:0] $end
$var wire 4 ( f_icode [3:0] $end
$var reg 64 ) f_pc [63:0] $end
$var reg 80 * inst [79:0] $end
$var reg 1 + mem_error $end
$scope module fetch0 $end
$var wire 64 , f_pc_i [63:0] $end
$var wire 80 - inst_i [79:0] $end
$var wire 1 + mem_error_i $end
$var reg 4 . f_icode_o [3:0] $end
$var reg 4 / f_ifun_o [3:0] $end
$var reg 64 0 f_predPC_o [63:0] $end
$var reg 4 1 f_rA_o [3:0] $end
$var reg 4 2 f_rB_o [3:0] $end
$var reg 3 3 f_stat_o [2:0] $end
$var reg 64 4 f_valC_o [63:0] $end
$var reg 64 5 f_valP_o [63:0] $end
$upscope $end
$upscope $end
$enddefinitions $end
#0
$dumpvars
b10 5
b0 4
b100 3
b1111 2
b1111 1
b10 0
b0 /
b0 .
b10101100000000000000000000000000000000000000000000000000000000000000000 -
b1 ,
0+
b10101100000000000000000000000000000000000000000000000000000000000000000 *
b1 )
b0 (
b0 '
b10 &
b1111 %
b1111 $
b100 #
b0 "
b10 !
$end
#50000
b10 &
b10 0
b0 #
b0 3
b10 !
b10 5
b1 (
b1 .
b10000010101100000000000000000000000000000000000000000000000000000000000000000 *
b10000010101100000000000000000000000000000000000000000000000000000000000000000 -
#100000
b110 $
b110 2
b101 %
b101 1
b11 &
b11 0
b11 !
b11 5
b10 (
b10 .
b100000010101100000000000000000000000000000000000000000000000000000000000000000 *
b100000010101100000000000000000000000000000000000000000000000000000000000000000 -
#150000
b100100000000000000000000000000000000000000000000000000000000 "
b100100000000000000000000000000000000000000000000000000000000 4
b1011 &
b1011 0
b1011 !
b1011 5
b110 $
b110 2
b101 %
b101 1
b11 (
b11 .
b110000010101100000000000000000000000000000000000000000000000000000000000001001 *
b110000010101100000000000000000000000000000000000000000000000000000000000001001 -
#200000
b1011 &
b1011 0
b1011 !
b1011 5
b11100000001000000000000000000000000000000000000000000000000 "
b11100000001000000000000000000000000000000000000000000000000 4
b110 $
b110 2
b101 %
b101 1
b100 (
b100 .
b1000000010101100000000000000000000000000000000000000000000000000000000100000111 *
b1000000010101100000000000000000000000000000000000000000000000000000000100000111 -
#250000
b1011 &
b1011 0
b1011 !
b1011 5
b1000000000000000000000000000000000000000000000000 "
b1000000000000000000000000000000000000000000000000 4
b110 $
b110 2
b101 %
b101 1
b101 (
b101 .
b1010000010101100000000000000000000000000000000000000000000000000000000100000000 *
b1010000010101100000000000000000000000000000000000000000000000000000000100000000 -
#300000
b11 &
b11 0
b11 !
b11 5
b0 "
b0 4
b110 $
b110 2
b101 %
b101 1
b110 (
b110 .
b1100000010101100000000000000000000000000000000000000000000000000000000000000000 *
b1100000010101100000000000000000000000000000000000000000000000000000000000000000 -
#350000
b1010110 "
b1010110 4
b1010110 &
b1010110 0
b1010 !
b1010 5
b1111 $
b1111 2
b1111 %
b1111 1
b111 (
b111 .
b1110000010101100000000000000000000000000000000000000000000000000000000000100000 *
b1110000010101100000000000000000000000000000000000000000000000000000000000100000 -
#400000
b100 $
b100 2
b100 %
b100 1
b1010110 &
b1010110 0
b1010 !
b1010 5
b1010110 "
b1010110 4
b1000 (
b1000 .
b10000000010101100000000000000000000000000000000000000000000000000000000000110001 *
b10000000010101100000000000000000000000000000000000000000000000000000000000110001 -
#450000
b0 &
b0 0
b10 !
b10 5
b0 "
b0 4
b100 $
b100 2
b100 %
b100 1
b1001 (
b1001 .
b10010000010101100000000000000000000000000000000000000000000000000000000000000000 *
b10010000010101100000000000000000000000000000000000000000000000000000000000000000 -
#500000
b11 &
b11 0
b11 !
b11 5
b100 $
b100 2
b101 %
b101 1
b1010 (
b1010 .
b10100000010101100000000000000000000000000000000000000000000000000000000000000000 *
b10100000010101100000000000000000000000000000000000000000000000000000000000000000 -
#550000
b11 &
b11 0
b11 !
b11 5
b100 $
b100 2
b101 %
b101 1
b1011 (
b1011 .
b10110000010101100000000000000000000000000000000000000000000000000000000000000000 *
b10110000010101100000000000000000000000000000000000000000000000000000000000000000 -
