refile testing/define.v
// Global macros
`define RST_EN      1'B1
`define TRUE        1'B1
`define FALSE       1'B0
`define SAOK        3'B000
`define SINS        3'B001
`define SADR        3'B010
`define SHLT        3'B100

// Instruction codes
`define HALT    4'H0
`define NOP     4'H1
`define CXX     4'H2
`define IXX     4'H3  //name to be changed
`define RMMOVQ  4'H4
`define MRMOVQ  4'H5
`define OPQ     4'H6
`define JXX     4'H7
`define CALL    4'H8
`define RET     4'H9
`define PUSHQ   4'HA
`define POPQ    4'HB

// Instruction functions
`define RRMOVQ  4'H0
`define CMOVLE  4'H1
`define CMOVL   4'H2
`define CMOVE   4'H3
`define CMOVNE  4'H4
`define CMOVGE  4'H5
`define CMOVG   4'H6

`define IRMOVQ  4'H0
`define IADDQ   4'H1
`define ISUBQ   4'H2
`define IANDQ   4'H3
`define IXORQ   4'H4

`define ADDQ    4'H0
`define SUBQ    4'H1
`define ANDQ    4'H2
`define XORQ    4'H3
`define NOPQ    4'H4

`define JMP     4'H0
`define JLE     4'H1
`define JL      4'H2
`define JE      4'H3
`define JNE     4'H4
`define JGE     4'H5
`define JG      4'H6

// Registers
`define RAX     4'H0
`define RBX     4'H3
`define RCX     4'H1
`define RDX     4'H2
`define RSP     4'H4
`define RBP     4'H5
`define RSI     4'H6
`define RDI     4'H7
`define R8      4'H8
`define R9      4'H9
`define R10     4'HA
`define R11     4'HB
`define R12     4'HC
`define R13     4'HD
`define R14     4'HE
`define NREG    4'HF

// Data width
`define ICODE_WIDTH     4
`define IFUN_WIDTH      4
`define BYTE_WIDTH      8
`define ADDR_WIDTH      64
`define DATA_WIDTH      64
`define INST_WIDTH      80

// Buses
`define IFUN_BUS        3:0
`define ICODE_BUS       3:0
`define REG_ADDR_BUS    3:0
`define ADDR_BUS        63:0
`define INST_BUS        79:0
`define DATA_BUS        63:0
`define STAT_BUS        2:0

// Instruction parts
`define ICODE           79:76
`define IFUN            75:72
`define SRCA            71:68
`define SRCB            67:64
`define BYTE8           71:64
`define BYTE7           63:56
`define BYTE6           55:48
`define BYTE5           47:40
`define BYTE4           39:32
`define BYTE3           31:24
`define BYTE2           23:16
`define BYTE1           15:8
`define BYTE0           7:0

// Memory size
`define MEM_SIZE        131071

// Default values
`define ICODE_ZERO      `ICODE_WIDTH'H0
`define IFUN_ZERO       `IFUN_WIDTH'H0
`define DATA_ZERO       `DATA_WIDTH'H0
`define ADDR_ZERO       `ADDR_WIDTH'H0
`define NONE_INST       `INST_WIDTH'H0
`define BYTE_ZERO       `BYTE_WIDTH'H0

updatereg.v

module updatereg(in,enable,rst,resetval,clk,out);
parameter width = 64;
output reg [width-1:0] out;
input wire [width-1:0] in,resetval;
input wire enable,rst,clk;


always @(posedge clk)
begin
	if (rst)
		out <= resetval;
	else if (enable)
		out <= in;
end

endmodule

refile testing/rgfile.v
`include "define.v"
`include "updatereg.v"

module rgfile(rst,clk,W_dstE_i, W_valE_i, W_dstM_i, W_valM_i, d_srcA_i, d_rvalA_o, d_srcB_i, d_rvalB_o, rax, rcx, rdx, rbx, rsp, rbp, rsi, rdi, r8, r9, r10, r11, r12, r13, r14);

input wire [3:0] W_dstE_i,W_dstM_i,d_srcA_i,d_srcB_i;
input wire [63:0] W_valE_i,W_valM_i;
input wire rst,clk; 

output wire [63:0] d_rvalA_o,d_rvalB_o;
output wire [63:0] rax, rcx, rdx, rbx, rsp, rbp, rsi, rdi,
r8, r9, r10, r11, r12, r13, r14;


wire [63:0] rax_dat, rcx_dat, rdx_dat, rbx_dat, rsp_dat, rbp_dat, rsi_dat, rdi_dat,
r8_dat, r9_dat, r10_dat, r11_dat, r12_dat, r13_dat, r14_dat;

wire rax_wrt, rcx_wrt, rdx_wrt, rbx_wrt, rsp_wrt, rbp_wrt, rsi_wrt, rdi_wrt,
r8_wrt, r9_wrt, r10_wrt, r11_wrt, r12_wrt, r13_wrt, r14_wrt;


// Implement with clked registers

updatereg rax_reg(rax_dat, rax_wrt, rst, 64'b0, clk, rax);
updatereg rcx_reg(rcx_dat, rcx_wrt, rst, 64'b0, clk, rcx);
updatereg rdx_reg(rdx_dat, rdx_wrt, rst, 64'b0, clk, rdx);
updatereg rbx_reg(rbx_dat, rbx_wrt, rst, 64'b0, clk, rbx);
updatereg rsp_reg(rsp_dat, rsp_wrt, rst, 64'b0, clk, rsp);
updatereg rbp_reg(rbp_dat, rbp_wrt, rst, 64'b0, clk, rbp);
updatereg rsi_reg(rsi_dat, rsi_wrt, rst, 64'b0, clk, rsi);
updatereg rdi_reg(rdi_dat, rdi_wrt, rst, 64'b0, clk, rdi);
updatereg r8_reg(r8_dat, r8_wrt, rst, 64'b0, clk, r8);
updatereg r9_reg(r9_dat, r9_wrt, rst, 64'b0, clk, r9);
updatereg r10_reg(r10_dat, r10_wrt, rst, 64'b0, clk, r10);
updatereg r11_reg(r11_dat, r11_wrt, rst, 64'b0, clk, r11);
updatereg r12_reg(r12_dat, r12_wrt, rst, 64'b0, clk, r12);
updatereg r13_reg(r13_dat, r13_wrt, rst, 64'b0, clk, r13);
updatereg r14_reg(r14_dat, r14_wrt, rst, 64'b0, clk, r14);


// Reads occur like combinational logic

assign d_rvalA_o =
d_srcA_i == `RAX ? rax:
d_srcA_i == `RCX ? rcx:
d_srcA_i == `RDX ? rdx:
d_srcA_i == `RBX ? rbx:
d_srcA_i == `RSP ? rsp:
d_srcA_i == `RBP ? rbp:
d_srcA_i == `RSI ? rsi:
d_srcA_i == `RDI ? rdi:
d_srcA_i == `R8 ? r8:
d_srcA_i == `R9 ? r9:
d_srcA_i == `R10 ? r10:
d_srcA_i == `R11 ? r11:
d_srcA_i == `R12 ? r12:
d_srcA_i == `R13 ? r13:
d_srcA_i == `R14 ? r14:0;

assign d_rvalB_o =
d_srcB_i == `RAX ? rax:
d_srcB_i == `RCX ? rcx:
d_srcB_i == `RDX ? rdx:
d_srcB_i == `RBX ? rbx:
d_srcB_i == `RSP ? rsp:
d_srcB_i == `RBP ? rbp:
d_srcB_i == `RSI ? rsi:
d_srcB_i == `RDI ? rdi :
d_srcB_i == `R8 ? r8:
d_srcB_i == `R9 ? r9:
d_srcB_i == `R10 ? r10:
d_srcB_i == `R11 ? r11:
d_srcB_i == `R12 ? r12:
d_srcB_i == `R13 ? r13:
d_srcB_i == `R14 ? r14:0;



assign rax_dat = W_dstM_i == `RAX ? W_valM_i : W_valE_i;
assign rcx_dat = W_dstM_i == `RCX ? W_valM_i : W_valE_i;
assign rdx_dat = W_dstM_i == `RDX ? W_valM_i : W_valE_i;
assign rbx_dat = W_dstM_i == `RBX ? W_valM_i : W_valE_i;
assign rsp_dat = W_dstM_i == `RSP ? W_valM_i : W_valE_i;
assign rbp_dat = W_dstM_i == `RBP ? W_valM_i : W_valE_i;
assign rsi_dat = W_dstM_i == `RSI ? W_valM_i : W_valE_i;
assign rdi_dat = W_dstM_i == `RDI ? W_valM_i : W_valE_i;
assign r8_dat = W_dstM_i == `R8 ? W_valM_i : W_valE_i;
assign r9_dat = W_dstM_i == `R9 ? W_valM_i : W_valE_i;
assign r10_dat = W_dstM_i == `R10 ? W_valM_i : W_valE_i;
assign r11_dat = W_dstM_i == `R11 ? W_valM_i : W_valE_i;
assign r12_dat = W_dstM_i == `R12 ? W_valM_i : W_valE_i;
assign r13_dat = W_dstM_i == `R13 ? W_valM_i : W_valE_i;
assign r14_dat = W_dstM_i == `R14 ? W_valM_i : W_valE_i;


assign rax_wrt = W_dstM_i == `RAX | W_dstE_i == `RAX;
assign rcx_wrt = W_dstM_i == `RCX | W_dstE_i == `RCX;
assign rdx_wrt = W_dstM_i == `RDX | W_dstE_i == `RDX;
assign rbx_wrt = W_dstM_i == `RBX | W_dstE_i == `RBX;
assign rsp_wrt = W_dstM_i == `RSP | W_dstE_i == `RSP;
assign rbp_wrt = W_dstM_i == `RBP | W_dstE_i == `RBP;
assign rsi_wrt = W_dstM_i == `RSI | W_dstE_i == `RSI;
assign rdi_wrt = W_dstM_i == `RDI | W_dstE_i == `RDI;
assign r8_wrt = W_dstM_i == `R8 | W_dstE_i == `R8;
assign r9_wrt = W_dstM_i == `R9 | W_dstE_i == `R9;
assign r10_wrt = W_dstM_i == `R10 | W_dstE_i == `R10;
assign r11_wrt = W_dstM_i == `R11 | W_dstE_i == `R11;
assign r12_wrt = W_dstM_i == `R12 | W_dstE_i == `R12;
assign r13_wrt = W_dstM_i == `R13 | W_dstE_i == `R13;
assign r14_wrt = W_dstM_i == `R14 | W_dstE_i == `R14;

endmodule

refile testing/rgfile_tb.v
`timescale 1ns/1ps
`include "define.v"

module rgfile_tb;
	
	reg [63:0] W_valE_i , W_valM_i ;
	reg [3:0] W_dstE_i , W_dstM_i ,  d_srcA_i, d_srcB_i;
	reg [0:0] clk , rst ;
	wire [63:0] d_rvalA_o, d_rvalB_o ;

	integer cnt ;
	wire [63:0] rax, rcx, rdx, rbx, rsp, rbp, rsi, rdi,
r8, r9, r10, r11, r12, r13, r14;
	
	rgfile r0(rst,clk,W_dstE_i, W_valE_i, W_dstM_i, W_valM_i, d_srcA_i, d_rvalA_o, d_srcB_i, d_rvalB_o, rax, rcx, rdx, rbx, rsp, rbp, rsi, rdi, r8, r9, r10, r11, r12, r13, r14);
	
	initial
		begin
			$dumpfile("rgfile_tb.vcd") ;
			$dumpvars(0,rgfile_tb) ;
		end
		
	initial
		begin
			#1 ;
			rst = 1 ;
			#10 
			rst = 0 ;
			W_dstM_i = 4'hf ;
			W_dstE_i = 4'h0 ;
			W_valE_i = 64'h13 ;
			#10 		 ;	
		end
	
	initial
		begin
			$monitor("rax_out = %h\nvalA = %h\nvalB = %h\n valE=%h\nvalM=%h\n" ,rax  , d_rvalA_o, d_rvalB_o ,W_valE_i , W_valM_i ) ;
		end
	
	initial
		begin
			cnt = 0 ;
			clk = 0 ;
			#5 ;
			
			while ( cnt < 11 )
				begin
					clk = ~clk ;
					cnt = cnt + 1 ;
					#5 ;
				end
		end
endmodule

refile testing/rgfile_tb.vcd
$date
	Wed Mar 10 17:21:46 2021
$end
$version
	Icarus Verilog
$end
$timescale
	1ps
$end
$scope module rgfile_tb $end
$var wire 64 ! rsp [63:0] $end
$var wire 64 " rsi [63:0] $end
$var wire 64 # rdx [63:0] $end
$var wire 64 $ rdi [63:0] $end
$var wire 64 % rcx [63:0] $end
$var wire 64 & rbx [63:0] $end
$var wire 64 ' rbp [63:0] $end
$var wire 64 ( rax [63:0] $end
$var wire 64 ) r9 [63:0] $end
$var wire 64 * r8 [63:0] $end
$var wire 64 + r14 [63:0] $end
$var wire 64 , r13 [63:0] $end
$var wire 64 - r12 [63:0] $end
$var wire 64 . r11 [63:0] $end
$var wire 64 / r10 [63:0] $end
$var wire 64 0 d_rvalB_o [63:0] $end
$var wire 64 1 d_rvalA_o [63:0] $end
$var reg 4 2 W_dstE_i [3:0] $end
$var reg 4 3 W_dstM_i [3:0] $end
$var reg 64 4 W_valE_i [63:0] $end
$var reg 64 5 W_valM_i [63:0] $end
$var reg 1 6 clk $end
$var reg 4 7 d_srcA_i [3:0] $end
$var reg 4 8 d_srcB_i [3:0] $end
$var reg 1 9 rst $end
$var integer 32 : cnt [31:0] $end
$scope module r0 $end
$var wire 4 ; W_dstE_i [3:0] $end
$var wire 4 < W_dstM_i [3:0] $end
$var wire 64 = W_valE_i [63:0] $end
$var wire 64 > W_valM_i [63:0] $end
$var wire 1 6 clk $end
$var wire 4 ? d_srcA_i [3:0] $end
$var wire 4 @ d_srcB_i [3:0] $end
$var wire 1 A r10_wrt $end
$var wire 1 B r11_wrt $end
$var wire 1 C r12_wrt $end
$var wire 1 D r13_wrt $end
$var wire 1 E r14_wrt $end
$var wire 1 F r8_wrt $end
$var wire 1 G r9_wrt $end
$var wire 1 H rax_wrt $end
$var wire 1 I rbp_wrt $end
$var wire 1 J rbx_wrt $end
$var wire 1 K rcx_wrt $end
$var wire 1 L rdi_wrt $end
$var wire 1 M rdx_wrt $end
$var wire 1 N rsi_wrt $end
$var wire 1 O rsp_wrt $end
$var wire 1 9 rst $end
$var wire 64 P rsp_dat [63:0] $end
$var wire 64 Q rsp [63:0] $end
$var wire 64 R rsi_dat [63:0] $end
$var wire 64 S rsi [63:0] $end
$var wire 64 T rdx_dat [63:0] $end
$var wire 64 U rdx [63:0] $end
$var wire 64 V rdi_dat [63:0] $end
$var wire 64 W rdi [63:0] $end
$var wire 64 X rcx_dat [63:0] $end
$var wire 64 Y rcx [63:0] $end
$var wire 64 Z rbx_dat [63:0] $end
$var wire 64 [ rbx [63:0] $end
$var wire 64 \ rbp_dat [63:0] $end
$var wire 64 ] rbp [63:0] $end
$var wire 64 ^ rax_dat [63:0] $end
$var wire 64 _ rax [63:0] $end
$var wire 64 ` r9_dat [63:0] $end
$var wire 64 a r9 [63:0] $end
$var wire 64 b r8_dat [63:0] $end
$var wire 64 c r8 [63:0] $end
$var wire 64 d r14_dat [63:0] $end
$var wire 64 e r14 [63:0] $end
$var wire 64 f r13_dat [63:0] $end
$var wire 64 g r13 [63:0] $end
$var wire 64 h r12_dat [63:0] $end
$var wire 64 i r12 [63:0] $end
$var wire 64 j r11_dat [63:0] $end
$var wire 64 k r11 [63:0] $end
$var wire 64 l r10_dat [63:0] $end
$var wire 64 m r10 [63:0] $end
$var wire 64 n d_rvalB_o [63:0] $end
$var wire 64 o d_rvalA_o [63:0] $end
$scope module r10_reg $end
$var wire 1 6 clk $end
$var wire 1 A enable $end
$var wire 64 p in [63:0] $end
$var wire 64 q resetval [63:0] $end
$var wire 1 9 rst $end
$var reg 64 r out [63:0] $end
$upscope $end
$scope module r11_reg $end
$var wire 1 6 clk $end
$var wire 1 B enable $end
$var wire 64 s in [63:0] $end
$var wire 64 t resetval [63:0] $end
$var wire 1 9 rst $end
$var reg 64 u out [63:0] $end
$upscope $end
$scope module r12_reg $end
$var wire 1 6 clk $end
$var wire 1 C enable $end
$var wire 64 v in [63:0] $end
$var wire 64 w resetval [63:0] $end
$var wire 1 9 rst $end
$var reg 64 x out [63:0] $end
$upscope $end
$scope module r13_reg $end
$var wire 1 6 clk $end
$var wire 1 D enable $end
$var wire 64 y in [63:0] $end
$var wire 64 z resetval [63:0] $end
$var wire 1 9 rst $end
$var reg 64 { out [63:0] $end
$upscope $end
$scope module r14_reg $end
$var wire 1 6 clk $end
$var wire 1 E enable $end
$var wire 64 | in [63:0] $end
$var wire 64 } resetval [63:0] $end
$var wire 1 9 rst $end
$var reg 64 ~ out [63:0] $end
$upscope $end
$scope module r8_reg $end
$var wire 1 6 clk $end
$var wire 1 F enable $end
$var wire 64 !" in [63:0] $end
$var wire 64 "" resetval [63:0] $end
$var wire 1 9 rst $end
$var reg 64 #" out [63:0] $end
$upscope $end
$scope module r9_reg $end
$var wire 1 6 clk $end
$var wire 1 G enable $end
$var wire 64 $" in [63:0] $end
$var wire 64 %" resetval [63:0] $end
$var wire 1 9 rst $end
$var reg 64 &" out [63:0] $end
$upscope $end
$scope module rax_reg $end
$var wire 1 6 clk $end
$var wire 1 H enable $end
$var wire 64 '" in [63:0] $end
$var wire 64 (" resetval [63:0] $end
$var wire 1 9 rst $end
$var reg 64 )" out [63:0] $end
$upscope $end
$scope module rbp_reg $end
$var wire 1 6 clk $end
$var wire 1 I enable $end
$var wire 64 *" in [63:0] $end
$var wire 64 +" resetval [63:0] $end
$var wire 1 9 rst $end
$var reg 64 ," out [63:0] $end
$upscope $end
$scope module rbx_reg $end
$var wire 1 6 clk $end
$var wire 1 J enable $end
$var wire 64 -" in [63:0] $end
$var wire 64 ." resetval [63:0] $end
$var wire 1 9 rst $end
$var reg 64 /" out [63:0] $end
$upscope $end
$scope module rcx_reg $end
$var wire 1 6 clk $end
$var wire 1 K enable $end
$var wire 64 0" in [63:0] $end
$var wire 64 1" resetval [63:0] $end
$var wire 1 9 rst $end
$var reg 64 2" out [63:0] $end
$upscope $end
$scope module rdi_reg $end
$var wire 1 6 clk $end
$var wire 1 L enable $end
$var wire 64 3" in [63:0] $end
$var wire 64 4" resetval [63:0] $end
$var wire 1 9 rst $end
$var reg 64 5" out [63:0] $end
$upscope $end
$scope module rdx_reg $end
$var wire 1 6 clk $end
$var wire 1 M enable $end
$var wire 64 6" in [63:0] $end
$var wire 64 7" resetval [63:0] $end
$var wire 1 9 rst $end
$var reg 64 8" out [63:0] $end
$upscope $end
$scope module rsi_reg $end
$var wire 1 6 clk $end
$var wire 1 N enable $end
$var wire 64 9" in [63:0] $end
$var wire 64 :" resetval [63:0] $end
$var wire 1 9 rst $end
$var reg 64 ;" out [63:0] $end
$upscope $end
$scope module rsp_reg $end
$var wire 1 6 clk $end
$var wire 1 O enable $end
$var wire 64 <" in [63:0] $end
$var wire 64 =" resetval [63:0] $end
$var wire 1 9 rst $end
$var reg 64 >" out [63:0] $end
$upscope $end
$upscope $end
$upscope $end
$enddefinitions $end
#0
$dumpvars
bx >"
b0 ="
bx <"
bx ;"
b0 :"
bx 9"
bx 8"
b0 7"
bx 6"
bx 5"
b0 4"
bx 3"
bx 2"
b0 1"
bx 0"
bx /"
b0 ."
bx -"
bx ,"
b0 +"
bx *"
bx )"
b0 ("
bx '"
bx &"
b0 %"
bx $"
bx #"
b0 ""
bx !"
bx ~
b0 }
bx |
bx {
b0 z
bx y
bx x
b0 w
bx v
bx u
b0 t
bx s
bx r
b0 q
bx p
bx o
bx n
bx m
bx l
bx k
bx j
bx i
bx h
bx g
bx f
bx e
bx d
bx c
bx b
bx a
bx `
bx _
bx ^
bx ]
bx \
bx [
bx Z
bx Y
bx X
bx W
bx V
bx U
bx T
bx S
bx R
bx Q
bx P
xO
xN
xM
xL
xK
xJ
xI
xH
xG
xF
xE
xD
xC
xB
xA
bx @
bx ?
bx >
bx =
bx <
bx ;
b0 :
x9
bx 8
bx 7
06
bx 5
bx 4
bx 3
bx 2
bx 1
bx 0
bx /
bx .
bx -
bx ,
bx +
bx *
bx )
bx (
bx '
bx &
bx %
bx $
bx #
bx "
bx !
$end
#1000
19
#5000
b0 0
b0 n
b0 1
b0 o
b0 (
b0 _
b0 )"
b0 %
b0 Y
b0 2"
b0 #
b0 U
b0 8"
b0 &
b0 [
b0 /"
b0 !
b0 Q
b0 >"
b0 '
b0 ]
b0 ,"
b0 "
b0 S
b0 ;"
b0 $
b0 W
b0 5"
b0 *
b0 c
b0 #"
b0 )
b0 a
b0 &"
b0 /
b0 m
b0 r
b0 .
b0 k
b0 u
b0 -
b0 i
b0 x
b0 ,
b0 g
b0 {
b0 +
b0 e
b0 ~
b1 :
16
#10000
b10 :
06
#11000
b10011 ^
b10011 '"
b10011 X
b10011 0"
b10011 T
b10011 6"
b10011 Z
b10011 -"
b10011 P
b10011 <"
b10011 \
b10011 *"
b10011 R
b10011 9"
b10011 V
b10011 3"
b10011 b
b10011 !"
b10011 `
b10011 $"
b10011 l
b10011 p
b10011 j
b10011 s
b10011 h
b10011 v
b10011 f
b10011 y
b10011 d
b10011 |
1H
0K
0M
0J
0O
0I
0N
0L
0F
0G
0A
0B
0C
0D
0E
b10011 4
b10011 =
b0 2
b0 ;
b1111 3
b1111 <
09
#15000
b0x00xx 0
b0x00xx n
b0x00xx 1
b0x00xx o
b10011 (
b10011 _
b10011 )"
b11 :
16
#20000
b100 :
06
#25000
b101 :
16
#30000
b110 :
06
#35000
b111 :
16
#40000
b1000 :
06
#45000
b1001 :
16
#50000
b1010 :
06
#55000
b1011 :
16
